{
    "codeToName": {
        "0": "NULL",
        "13": "CR",
        "32": "space",
        "33": "exclam",
        "34": "quotedbl",
        "35": "numbersign",
        "36": "dollar",
        "37": "percent",
        "38": "ampersand",
        "39": "quotesingle",
        "40": "parenleft",
        "41": "parenright",
        "42": "asterisk",
        "43": "plus",
        "44": "comma",
        "45": "hyphen",
        "46": "period",
        "47": "slash",
        "48": "zero",
        "49": "one",
        "50": "two",
        "51": "three",
        "52": "four",
        "53": "five",
        "54": "six",
        "55": "seven",
        "56": "eight",
        "57": "nine",
        "58": "colon",
        "59": "semicolon",
        "60": "less",
        "61": "equal",
        "62": "greater",
        "63": "question",
        "64": "at",
        "65": "A",
        "66": "B",
        "67": "C",
        "68": "D",
        "69": "E",
        "70": "F",
        "71": "G",
        "72": "H",
        "73": "I",
        "74": "J",
        "75": "K",
        "76": "L",
        "77": "M",
        "78": "N",
        "79": "O",
        "80": "P",
        "81": "Q",
        "82": "R",
        "83": "S",
        "84": "T",
        "85": "U",
        "86": "V",
        "87": "W",
        "88": "X",
        "89": "Y",
        "90": "Z",
        "91": "bracketleft",
        "92": "backslash",
        "93": "bracketright",
        "94": "asciicircum",
        "95": "underscore",
        "96": "grave",
        "97": "a",
        "98": "b",
        "99": "c",
        "100": "d",
        "101": "e",
        "102": "f",
        "103": "g",
        "104": "h",
        "105": "i",
        "106": "j",
        "107": "k",
        "108": "l",
        "109": "m",
        "110": "n",
        "111": "o",
        "112": "p",
        "113": "q",
        "114": "r",
        "115": "s",
        "116": "t",
        "117": "u",
        "118": "v",
        "119": "w",
        "120": "x",
        "121": "y",
        "122": "z",
        "123": "braceleft",
        "124": "bar",
        "125": "braceright",
        "126": "asciitilde",
        "160": "uni00A0",
        "161": "exclamdown",
        "162": "cent",
        "163": "sterling",
        "165": "yen",
        "167": "section",
        "168": "dieresis",
        "169": "copyright",
        "170": "ordfeminine",
        "171": "guillemotleft",
        "174": "registered",
        "175": "overscore",
        "176": "degree",
        "180": "acute",
        "182": "paragraph",
        "183": "periodcentered",
        "184": "cedilla",
        "186": "ordmasculine",
        "187": "guillemotright",
        "191": "questiondown",
        "192": "Agrave",
        "193": "Aacute",
        "194": "Acircumflex",
        "195": "Atilde",
        "196": "Adieresis",
        "197": "Aring",
        "198": "AE",
        "199": "Ccedilla",
        "200": "Egrave",
        "201": "Eacute",
        "202": "Ecircumflex",
        "203": "Edieresis",
        "204": "Igrave",
        "205": "Iacute",
        "206": "Icircumflex",
        "207": "Idieresis",
        "208": "Eth",
        "209": "Ntilde",
        "210": "Ograve",
        "211": "Oacute",
        "212": "Ocircumflex",
        "213": "Otilde",
        "214": "Odieresis",
        "215": "multiply",
        "216": "Oslash",
        "217": "Ugrave",
        "218": "Uacute",
        "219": "Ucircumflex",
        "220": "Udieresis",
        "221": "Yacute",
        "222": "Thorn",
        "223": "germandbls",
        "224": "agrave",
        "225": "aacute",
        "226": "acircumflex",
        "227": "atilde",
        "228": "adieresis",
        "229": "aring",
        "230": "ae",
        "231": "ccedilla",
        "232": "egrave",
        "233": "eacute",
        "234": "ecircumflex",
        "235": "edieresis",
        "236": "igrave",
        "237": "iacute",
        "238": "icircumflex",
        "239": "idieresis",
        "240": "eth",
        "241": "ntilde",
        "242": "ograve",
        "243": "oacute",
        "244": "ocircumflex",
        "245": "otilde",
        "246": "odieresis",
        "247": "divide",
        "248": "oslash",
        "249": "ugrave",
        "250": "uacute",
        "251": "ucircumflex",
        "252": "udieresis",
        "253": "yacute",
        "254": "thorn",
        "255": "ydieresis",
        "256": "Amacron",
        "257": "amacron",
        "258": "Abreve",
        "259": "abreve",
        "260": "Aogonek",
        "261": "aogonek",
        "262": "Cacute",
        "263": "cacute",
        "266": "Cdotaccent",
        "267": "cdotaccent",
        "268": "Ccaron",
        "269": "ccaron",
        "270": "Dcaron",
        "271": "dcaron",
        "272": "Dcroat",
        "273": "dmacron",
        "274": "Emacron",
        "275": "emacron",
        "278": "Edotaccent",
        "279": "edotaccent",
        "280": "Eogonek",
        "281": "eogonek",
        "282": "Ecaron",
        "283": "ecaron",
        "286": "Gbreve",
        "287": "gbreve",
        "288": "Gdotaccent",
        "289": "gdotaccent",
        "290": "uni0122",
        "291": "uni0123",
        "294": "Hbar",
        "295": "hbar",
        "298": "Imacron",
        "299": "imacron",
        "302": "Iogonek",
        "303": "iogonek",
        "304": "Idot",
        "305": "dotlessi",
        "310": "uni0136",
        "311": "uni0137",
        "313": "Lacute",
        "314": "lacute",
        "315": "uni013B",
        "316": "uni013C",
        "317": "Lcaron",
        "318": "lcaron",
        "321": "Lslash",
        "322": "lslash",
        "323": "Nacute",
        "324": "nacute",
        "325": "uni0145",
        "326": "uni0146",
        "327": "Ncaron",
        "328": "ncaron",
        "330": "Eng",
        "331": "eng",
        "332": "Omacron",
        "333": "omacron",
        "336": "Ohungarumlaut",
        "337": "ohungarumlaut",
        "338": "OE",
        "339": "oe",
        "340": "Racute",
        "341": "racute",
        "342": "uni0156",
        "343": "uni0157",
        "344": "Rcaron",
        "345": "rcaron",
        "346": "Sacute",
        "347": "sacute",
        "350": "Scedilla",
        "351": "scedilla",
        "352": "Scaron",
        "353": "scaron",
        "356": "Tcaron",
        "357": "tcaron",
        "362": "Umacron",
        "363": "umacron",
        "364": "Ubreve",
        "365": "ubreve",
        "366": "Uring",
        "367": "uring",
        "368": "Uhungarumlaut",
        "369": "uhungarumlaut",
        "370": "Uogonek",
        "371": "uogonek",
        "372": "Wcircumflex",
        "373": "wcircumflex",
        "374": "Ycircumflex",
        "375": "ycircumflex",
        "376": "Ydieresis",
        "377": "Zacute",
        "378": "zacute",
        "379": "Zdotaccent",
        "380": "zdotaccent",
        "381": "Zcaron",
        "382": "zcaron",
        "536": "uni0218",
        "537": "uni0219",
        "538": "uni021A",
        "539": "uni021B",
        "567": "uni0237",
        "710": "circumflex",
        "711": "caron",
        "713": "macronmod",
        "728": "breve",
        "729": "dotaccent",
        "730": "ring",
        "731": "ogonek",
        "732": "tilde",
        "733": "hungarumlaut",
        "768": "gravecomb",
        "769": "acutecomb",
        "770": "uni0302",
        "771": "tildecomb",
        "772": "uni0304",
        "774": "uni0306",
        "775": "uni0307",
        "776": "uni0308",
        "778": "uni030A",
        "779": "uni030B",
        "780": "uni030C",
        "786": "uni0312",
        "806": "uni0326",
        "807": "uni0327",
        "808": "uni0328",
        "2385": "uni0951",
        "2386": "uni0952",
        "2404": "uni0964.gujr",
        "2405": "uni0965.gujr",
        "2689": "candrabindugujr",
        "2690": "anusvaragujr",
        "2691": "visargagujr",
        "2693": "agujr",
        "2694": "aagujr",
        "2695": "igujr",
        "2696": "iigujr",
        "2697": "ugujr",
        "2698": "uugujr",
        "2699": "rvocalicgujr",
        "2700": "lvocalicgujr",
        "2701": "ecandragujr",
        "2703": "egujr",
        "2704": "aigujr",
        "2705": "ocandragujr",
        "2707": "ogujr",
        "2708": "augujr",
        "2709": "kagujr",
        "2710": "khagujr",
        "2711": "gagujr",
        "2712": "ghagujr",
        "2713": "ngagujr",
        "2714": "cagujr",
        "2715": "chagujr",
        "2716": "jagujr",
        "2717": "jhagujr",
        "2718": "nyagujr",
        "2719": "ttagujr",
        "2720": "tthagujr",
        "2721": "ddagujr",
        "2722": "ddhagujr",
        "2723": "nnagujr",
        "2724": "tagujr",
        "2725": "thagujr",
        "2726": "dagujr",
        "2727": "dhagujr",
        "2728": "nagujr",
        "2730": "pagujr",
        "2731": "phagujr",
        "2732": "bagujr",
        "2733": "bhagujr",
        "2734": "magujr",
        "2735": "yagujr",
        "2736": "ragujr",
        "2738": "lagujr",
        "2739": "llagujr",
        "2741": "vagujr",
        "2742": "shagujr",
        "2743": "ssagujr",
        "2744": "sagujr",
        "2745": "hagujr",
        "2748": "nuktagujr",
        "2749": "avagrahagujr",
        "2750": "aavowelsigngujr",
        "2751": "ivowelsigngujr",
        "2752": "iivowelsigngujr",
        "2753": "uvowelsigngujr",
        "2754": "uuvowelsigngujr",
        "2755": "rvocalicvowelsigngujr",
        "2756": "rrvocalicvowelsigngujr",
        "2757": "ecandravowelsigngujr",
        "2759": "evowelsigngujr",
        "2760": "aivowelsigngujr",
        "2761": "ocandravowelsigngujr",
        "2763": "ovowelsigngujr",
        "2764": "auvowelsigngujr",
        "2765": "viramagujr",
        "2768": "omgujr",
        "2784": "rrvocalicgujr",
        "2785": "llvocalicgujr",
        "2786": "lvocalicvowelsigngujr",
        "2787": "llvocalicvowelsigngujr",
        "2790": "zerogujr",
        "2791": "onegujr",
        "2792": "twogujr",
        "2793": "threegujr",
        "2794": "fourgujr",
        "2795": "fivegujr",
        "2796": "sixgujr",
        "2797": "sevengujr",
        "2798": "eightgujr",
        "2799": "ninegujr",
        "2800": "uni0AF0",
        "2801": "uni0AF1",
        "2809": "zhagujr",
        "2810": "uni0AFA",
        "2811": "uni0AFB",
        "2812": "uni0AFC",
        "2813": "uni0AFD",
        "2814": "uni0AFE",
        "2815": "uni0AFF",
        "7808": "Wgrave",
        "7809": "wgrave",
        "7810": "Wacute",
        "7811": "wacute",
        "7812": "Wdieresis",
        "7813": "wdieresis",
        "7838": "uni1E9E",
        "7922": "Ygrave",
        "7923": "ygrave",
        "8203": "uni200B",
        "8204": "uni200C",
        "8205": "uni200D",
        "8208": "uni2010",
        "8211": "endash",
        "8212": "emdash",
        "8216": "quoteleft",
        "8217": "quoteright",
        "8218": "quotesinglbase",
        "8220": "quotedblleft",
        "8221": "quotedblright",
        "8222": "quotedblbase",
        "8226": "bullet",
        "8230": "ellipsis",
        "8249": "guilsinglleft",
        "8250": "guilsinglright",
        "8364": "Euro",
        "8377": "uni20B9.gujr",
        "8482": "trademark",
        "8722": "minus",
        "9676": "uni25CC",
        "43056": "uniA830",
        "43057": "uniA831",
        "43058": "uniA832",
        "43059": "uniA833",
        "43060": "uniA834",
        "43061": "uniA835",
        "43062": "uniA836",
        "43063": "uniA837",
        "43064": "uniA838",
        "43065": "uniA839"
    },
    "isUnicode": true,
    "EncodingScheme": "FontSpecific",
    "FontName": "Noto Sans Gujarati ExtraLight",
    "FullName": "Noto Sans Gujarati ExtraLight",
    "Version": "Version 2.106",
    "PostScriptName": "NotoSansGujarati-ExtraLight",
    "Weight": "Medium",
    "ItalicAngle": "0",
    "IsFixedPitch": "false",
    "UnderlineThickness": "50",
    "UnderlinePosition": "-100",
    "FontHeightOffset": "0",
    "Ascender": "896",
    "Descender": "-408",
    "FontBBox": [
        "-825",
        "-395",
        "1250",
        "997"
    ],
    "StartCharMetrics": "1076",
    "C": {
        "0": 0,
        "13": 299,
        "32": 260,
        "33": 232,
        "34": 338,
        "35": 646,
        "36": 570,
        "37": 801,
        "38": 708,
        "39": 183,
        "40": 264,
        "41": 264,
        "42": 551,
        "43": 570,
        "44": 200,
        "45": 322,
        "46": 230,
        "47": 332,
        "48": 570,
        "49": 570,
        "50": 570,
        "51": 570,
        "52": 570,
        "53": 570,
        "54": 570,
        "55": 570,
        "56": 570,
        "57": 570,
        "58": 230,
        "59": 230,
        "60": 570,
        "61": 570,
        "62": 570,
        "63": 417,
        "64": 882,
        "65": 590,
        "66": 621,
        "67": 618,
        "68": 700,
        "69": 551,
        "70": 497,
        "71": 722,
        "72": 713,
        "73": 294,
        "74": 240,
        "75": 570,
        "76": 510,
        "77": 851,
        "78": 711,
        "79": 759,
        "80": 580,
        "81": 759,
        "82": 586,
        "83": 544,
        "84": 515,
        "85": 716,
        "86": 571,
        "87": 881,
        "88": 525,
        "89": 517,
        "90": 577,
        "91": 316,
        "92": 332,
        "93": 316,
        "94": 570,
        "95": 402,
        "96": 256,
        "97": 521,
        "98": 590,
        "99": 474,
        "100": 590,
        "101": 545,
        "102": 288,
        "103": 590,
        "104": 582,
        "105": 217,
        "106": 217,
        "107": 470,
        "108": 217,
        "109": 869,
        "110": 582,
        "111": 581,
        "112": 590,
        "113": 590,
        "114": 383,
        "115": 462,
        "116": 328,
        "117": 582,
        "118": 446,
        "119": 706,
        "120": 489,
        "121": 445,
        "122": 459,
        "123": 346,
        "124": 538,
        "125": 346,
        "126": 570,
        "160": 260,
        "161": 232,
        "162": 570,
        "163": 570,
        "165": 570,
        "167": 517,
        "168": 576,
        "169": 832,
        "170": 329,
        "171": 413,
        "174": 832,
        "175": 500,
        "176": 428,
        "180": 256,
        "182": 655,
        "183": 230,
        "184": 200,
        "186": 357,
        "187": 413,
        "191": 417,
        "192": 590,
        "193": 590,
        "194": 590,
        "195": 590,
        "196": 590,
        "197": 590,
        "198": 787,
        "199": 618,
        "200": 551,
        "201": 551,
        "202": 551,
        "203": 551,
        "204": 294,
        "205": 294,
        "206": 294,
        "207": 294,
        "208": 700,
        "209": 711,
        "210": 759,
        "211": 759,
        "212": 759,
        "213": 759,
        "214": 759,
        "215": 570,
        "216": 759,
        "217": 716,
        "218": 716,
        "219": 716,
        "220": 716,
        "221": 517,
        "222": 580,
        "223": 570,
        "224": 521,
        "225": 521,
        "226": 521,
        "227": 521,
        "228": 521,
        "229": 521,
        "230": 853,
        "231": 474,
        "232": 545,
        "233": 545,
        "234": 545,
        "235": 545,
        "236": 217,
        "237": 217,
        "238": 217,
        "239": 217,
        "240": 564,
        "241": 582,
        "242": 581,
        "243": 581,
        "244": 581,
        "245": 581,
        "246": 581,
        "247": 570,
        "248": 581,
        "249": 582,
        "250": 582,
        "251": 582,
        "252": 582,
        "253": 445,
        "254": 590,
        "255": 445,
        "256": 590,
        "257": 521,
        "258": 590,
        "259": 521,
        "260": 590,
        "261": 521,
        "262": 618,
        "263": 474,
        "266": 618,
        "267": 474,
        "268": 618,
        "269": 474,
        "270": 700,
        "271": 590,
        "272": 700,
        "273": 589,
        "274": 551,
        "275": 545,
        "278": 551,
        "279": 545,
        "280": 551,
        "281": 545,
        "282": 551,
        "283": 545,
        "286": 722,
        "287": 590,
        "288": 722,
        "289": 590,
        "290": 722,
        "291": 590,
        "294": 713,
        "295": 582,
        "298": 294,
        "299": 217,
        "302": 294,
        "303": 217,
        "304": 294,
        "305": 217,
        "310": 570,
        "311": 470,
        "313": 510,
        "314": 217,
        "315": 510,
        "316": 217,
        "317": 510,
        "318": 217,
        "321": 510,
        "322": 217,
        "323": 711,
        "324": 582,
        "325": 711,
        "326": 582,
        "327": 711,
        "328": 582,
        "330": 711,
        "331": 582,
        "332": 759,
        "333": 581,
        "336": 759,
        "337": 581,
        "338": 905,
        "339": 963,
        "340": 586,
        "341": 383,
        "342": 586,
        "343": 383,
        "344": 586,
        "345": 383,
        "346": 544,
        "347": 462,
        "350": 544,
        "351": 462,
        "352": 544,
        "353": 462,
        "356": 515,
        "357": 328,
        "362": 716,
        "363": 582,
        "364": 716,
        "365": 582,
        "366": 716,
        "367": 582,
        "368": 716,
        "369": 582,
        "370": 716,
        "371": 582,
        "372": 881,
        "373": 706,
        "374": 517,
        "375": 445,
        "376": 517,
        "377": 577,
        "378": 459,
        "379": 577,
        "380": 459,
        "381": 577,
        "382": 459,
        "536": 544,
        "537": 462,
        "538": 515,
        "539": 328,
        "567": 217,
        "710": 349,
        "711": 349,
        "713": 344,
        "728": 338,
        "729": 142,
        "730": 285,
        "731": 219,
        "732": 414,
        "733": 391,
        "768": 0,
        "769": 0,
        "770": 0,
        "771": 0,
        "772": 0,
        "774": 0,
        "775": 0,
        "776": 0,
        "778": 0,
        "779": 0,
        "780": 0,
        "786": 0,
        "806": 0,
        "807": 0,
        "808": 0,
        "2385": 0,
        "2386": 0,
        "2404": 344,
        "2405": 542,
        "2689": 0,
        "2690": 0,
        "2691": 209,
        "2693": 845,
        "2694": 1087,
        "2695": 598,
        "2696": 598,
        "2697": 600,
        "2698": 847,
        "2699": 810,
        "2700": 673,
        "2701": 845,
        "2703": 845,
        "2704": 845,
        "2705": 1087,
        "2707": 1087,
        "2708": 1087,
        "2709": 470,
        "2710": 713,
        "2711": 606,
        "2712": 599,
        "2713": 446,
        "2714": 635,
        "2715": 709,
        "2716": 784,
        "2717": 676,
        "2718": 655,
        "2719": 426,
        "2720": 485,
        "2721": 444,
        "2722": 487,
        "2723": 789,
        "2724": 542,
        "2725": 595,
        "2726": 450,
        "2727": 577,
        "2728": 511,
        "2730": 548,
        "2731": 470,
        "2732": 695,
        "2733": 773,
        "2734": 568,
        "2735": 557,
        "2736": 426,
        "2738": 614,
        "2739": 725,
        "2741": 553,
        "2742": 632,
        "2743": 558,
        "2744": 664,
        "2745": 607,
        "2748": 0,
        "2749": 453,
        "2750": 243,
        "2751": 243,
        "2752": 243,
        "2753": 0,
        "2754": 0,
        "2755": 0,
        "2756": 0,
        "2757": 0,
        "2759": 0,
        "2760": 0,
        "2761": 243,
        "2763": 243,
        "2764": 243,
        "2765": 0,
        "2768": 888,
        "2784": 872,
        "2785": 673,
        "2786": 0,
        "2787": 0,
        "2790": 551,
        "2791": 551,
        "2792": 551,
        "2793": 551,
        "2794": 551,
        "2795": 551,
        "2796": 551,
        "2797": 551,
        "2798": 551,
        "2799": 551,
        "2800": 369,
        "2801": 790,
        "2809": 784,
        "2810": 0,
        "2811": 0,
        "2812": 0,
        "2813": 0,
        "2814": 0,
        "2815": 0,
        "7808": 881,
        "7809": 706,
        "7810": 881,
        "7811": 706,
        "7812": 881,
        "7813": 706,
        "7838": 667,
        "7922": 517,
        "7923": 445,
        "8203": 0,
        "8204": 0,
        "8205": 0,
        "8208": 321,
        "8211": 500,
        "8212": 1000,
        "8216": 137,
        "8217": 137,
        "8218": 212,
        "8220": 284,
        "8221": 284,
        "8222": 363,
        "8226": 376,
        "8230": 695,
        "8249": 238,
        "8250": 238,
        "8364": 570,
        "8377": 551,
        "8482": 707,
        "8722": 322,
        "9676": 510,
        "43056": 198,
        "43057": 389,
        "43058": 580,
        "43059": 619,
        "43060": 619,
        "43061": 619,
        "43062": 453,
        "43063": 501,
        "43064": 278,
        "43065": 318
    },
    "CIDtoGID_Compressed": true,
    "CIDtoGID": "eJzt23VsHUcQx\/HJ\/sYh2yGHmR22w8zMzFBmZm7KzMzMbZiTBsrMzExhZuj1YkVRpaRu49hN8v1I92Zvd\/Z27vb0pPfHs1y2K2GXIzuTHtEKfaIbtFCHa71+1x86Rkt0qWZokefzdH3vKV5QT+hxz+t5dJc+0iWeW6\/rQY3XMh0bFoY1YW3YFLYqn\/KroAqrlEqrrCqpslJVXw3UUE3VSu3UQz3VT\/01RKfoBJ2qo7ysntMIHa8zdaVu1mN6UlM0Uwv0ol7Wm3pXn+pXLdUGN0\/0ol7BK3o1r+51dJJO1Mk6OlN3uPvbf1+PaqznN\/Na0ZGga3WFftCEeGyLftE1GXljouM3LdYFUfxREzN6l4flYXFYGlaHZWFVWBQ2yMM25VJQcRVRiooqr6qrjmqqltJVW+8oTZ3VXh3VSQPUVs\/qUI3UaB2ng3WkDtF5ulO36Dbdrrmapdmao4f0sb7RZ\/pcP+sLXa+fvJQX8xJe0lO9gNcMK3RYWKJRYaWOCOt0VrzxG3V+WK9zw2ZdFbboaiXonu1brTuURw\/IdGt8nqinlKxnlKSn4\/NCmhrHEpoXx5Kar2J6fsezKqOXos9yekUV9JrK69W4t6LeUBW9p2r6UFX1QdSTW\/ernr6LR+vqW9XQl2qkjWqizWqsTWrm8VurFi419\/g9VWtP2rFOVy+jDl5c3b28unhpdfNy6u2VNdBraJCGel0N9zQN83p7vv8HGrV0VxtP\/o+zX8jaavYvukhnR98h9Xebc5pu1FZ95YU0LUvWHKeDdLEX1ltR+3TdpOuiuE3Tdc5OOZdn8lqX6UJ9nRVVAQAAADgwhfFhQiayJoZJe78W7IfcEix3FPNYXstn+S3RkizZCljBqK+QFbYiUUyxolbMilsJK2mlrLSVsbJWzspbBatolayyVbGqVs2qW6rViLJrWi2rbXWsrtWztOg83f76Td\/AGloja2xN4lWbWjNrbi2spbWy1tbG2lq7qLe9dbCOUexkna1LnNf1H6rvZt2th\/WM272st\/WxvtbP+tsAG2iDbLANsaF\/mzHMhtsIG2mjbLSNyZpHCAAAAAAAAAAAAAAAAABA9lJfr6peXkl9vMq\/nltgb1SU9TTYa+d0DdiXhLlhXpgft+J\/b+s+3bt9RGu0VuuiuEqrtTKj74yMeHdmrq1JmpzV9f7\/6OFdjYRx2VlHdvAiOV0B9ia9ndMVAABwYAgLcroCAAAAAAAAAAAAAAAAAAAAAAAAAAAAAAAAAAAAAAAAAAAAAAAAAAAAAAAAAAAAAAAAAAAAAAAAAAAAAAAAAAAAAAAAAAAAAAAAAAAAAAAAAAAAAAAAAAAAAAAAAAAAAAAAYM+FyWFKmBqmhelhRpgZZoXZYU5O1wQAAAAAAAAAAAAAAAAAAAAAAAAAAAAAAAAAAAAAAAAAAAAAAAAAAAAAAAAAAAAAAAAAAAAAAAAAAAAAAAAAAAAA2Pf8CQnUvRw=",
    "_version_": 6
}